{
 "rule": {
        "id":1,
        "num_pvars":2,
 	"pvars":["pvar_max_vbuf_usage_index","pvar_vbuf_allocated_index"],
 	"cvars":["cvar1","cvar2[10]"],
	"operation": {
        	 "array": "pvar_max_vbuf_usage_index",
               	 "condition": {
			"stmt":"if",
                	"leftoperand": {
				"leftoperand":"pvar_vbuf_allocated_index",
              		     	"rightoperand":"pvar_max_vbuf_usage_index",
 			     	"operator":"-"	
			},
 			"rightoperand":"PVAR_VBUF_WASTED_THRESHOLD",
 			"operator":">"
        	},
		"result": {
			"leftoperand":"CVAR_SPECIFYING_REDUCED_POOL_SIZE",
			"rightoperand":"pvar_max_vbuf_usage_index",
			"operator":"="
		},
                "else": {
                	"leftoperand":"CVAR_SPECIFYING_REDUCED_POOL_SIZE",
  		       	"operator":"=",
                       	"rightoperand": {
                       		"leftoperand":"pvar_max_vbuf_allocated_index",
				"rightoperand":10,
 				"operator":"+"
                       	}	
               	}
       	}
  }
}
